{"$schema":"vscode://schemas/color-theme","name":"BeardedTheme Classics-anthracite","semanticHighlighting":true,"semanticTokenColors":{"property.declaration":{"foreground":"#bbbbbb"},"property":{"foreground":"#D26D32"},"variable":{"foreground":"#de456b"},"variable.defaultLibrary":{"foreground":"#24B5A8"},"class.declaration":{"foreground":"#935cd1"},"namespace":{"foreground":"#3398DB"},"parameter":{"foreground":"#CC71BC"},"class.decorator":{"foreground":"#CC71BC"},"enumMember":{"foreground":"#935cd1"}},"colors":{"contrastBorder":"#0b0c0e","activityBar.background":"#141519","activityBar.border":"#0b0c0e","activityBar.foreground":"#76808c","activityBar.inactiveForeground":"#464b52AA","activityBarBadge.background":"#76808c","activityBarBadge.foreground":"#141519","badge.background":"#76808c","badge.foreground":"#181a1f","breadcrumb.background":"#181a1f","breadcrumbPicker.background":"#181a1f","button.background":"#76808c75","button.foreground":"#bbbbbb","button.hoverBackground":"#76808c90","button.secondaryBackground":"#76808c20","button.secondaryForeground":"#bbbbbb","button.secondaryHoverBackground":"#76808c35","extensionButton.prominentBackground":"#76808c9d","extensionButton.prominentForeground":"#141519","extensionButton.prominentHoverBackground":"#76808c","charts.foreground":"#bbbbbb","charts.lines":"#bbbbbb","charts.red":"#C13838","charts.blue":"#3398DB","charts.yellow":"#c9a022","charts.orange":"#D26D32","charts.green":"#37ae6f","charts.purple":"#CC71BC","contrastActiveBorder":"#00000000","errorForeground":"#C13838","errorLens.hintForeground":"#3398DB99","errorLens.infoForeground":"#3398DB99","errorLens.errorForeground":"#C1383899","errorLens.warningForeground":"#c9a02299","focusBorder":"#76808c40","foreground":"#A4A4A4AA","icon.foreground":"#A4A4A4AA","selection.background":"#76808c60","widget.shadow":"#0b0c0e30","commandCenter.border":"#0b0c0e","commandCenter.background":"#181a1f","commandCenter.activeBackground":"#26282e60","commandCenter.activeForeground":"#A4A4A490","commandCenter.foreground":"#464b52","checkbox.foreground":"#bbbbbb","debugExceptionWidget.background":"#26282e","debugExceptionWidget.border":"#0b0c0e","debugToolBar.background":"#26282e","toolbar.hoverBackground":"#464b5260","descriptionForeground":"#bbbbbb","diffEditor.border":"#0b0c0e","diffEditor.insertedTextBackground":"#37ae6f20","diffEditor.removedTextBackground":"#C1383825","diffEditor.diagonalFill":"#0b0c0e80","diffEditorGutter.insertedLineBackground":"#00000000","diffEditorGutter.removedLineBackground":"#00000000","editorInlayHint.background":"#A4A4A420","editorInlayHint.foreground":"#A4A4A490","editorInlayHint.typeBackground":"#935cd130","editorInlayHint.typeForeground":"#935cd1aa","editorGhostText.border":"#00000000","editorGhostText.foreground":"#37ae6f70","editorGhostText.background":"#37ae6f10","editorCursor.background":"#76808c","editorBracketHighlight.foreground1":"#c9a022","editorBracketHighlight.foreground2":"#935cd1","editorBracketHighlight.foreground3":"#3398DB","editor.background":"#181a1f","editor.findMatchBackground":"#76808c20","editor.findMatchBorder":"#76808c60","editor.findMatchHighlightBackground":"#76808c20","dart.closingLabels":"#A4A4A4aa","editor.findMatchHighlightBorder":"#76808c40","editor.foreground":"#bbbbbb","editor.hoverHighlightBackground":"#76808c40","editor.lineHighlightBackground":"#76808c0c","editor.lineHighlightBorder":"#76808c1a","editor.rangeHighlightBackground":"#76808c20","editor.selectionBackground":"#76808c25","editor.selectionForeground":"#76808c","editor.inactiveSelectionBackground":"#76808c20","editor.selectionHighlightBorder":"#76808c60","editor.selectionHighlightBackground":"#00000000","editor.wordHighlightStrongBackground":"#76808c40","editor.wordHighlightBackground":"#76808c20","editorBracketMatch.background":"#76808c20","editorBracketMatch.border":"#76808c40","editorCodeLens.foreground":"#A4A4A480","editorCursor.foreground":"#c9a022","editorGroup.border":"#0b0c0e","editorGroup.dropBackground":"#76808c15","editorHoverWidget.background":"#26282e","editorHoverWidget.border":"#0b0c0e","editorIndentGuide.background":"#464b5230","editorIndentGuide.activeBackground":"#464b52bb","editorLink.activeForeground":"#bbbbbb","editorGutter.commentRangeForeground":"#26282e","sash.hoverBorder":"#76808c50","editorRuler.foreground":"#0b0c0e40","editorWarning.foreground":"#c9a022","editorWhitespace.foreground":"#464b5260","editorWidget.background":"#26282e","editorWidget.resizeBorder":"#76808c50","editorGutter.background":"#181a1f","editorGutter.addedBackground":"#37ae6fcc","editorGutter.deletedBackground":"#C13838cc","editorGutter.modifiedBackground":"#3398DBcc","editorLineNumber.foreground":"#464b5290","editorLineNumber.activeForeground":"#464b52","dropdown.background":"#181a1f","dropdown.listBackground":"#181a1f","dropdown.foreground":"#bbbbbb","dropdown.border":"#464b5250","input.background":"#00000000","input.foreground":"#bbbbbb","input.border":"#464b5250","input.placeholderForeground":"#bbbbbb60","inputOption.activeBorder":"#76808c","inputValidation.errorBackground":"#26282e","inputValidation.errorBorder":"#c9a022","inputValidation.infoBackground":"#26282e","inputValidation.infoBorder":"#76808c","inputValidation.warningBackground":"#26282e","inputValidation.warningBorder":"#c9a022","list.dropBackground":"#76808c15","list.focusBackground":"#76808c40","list.focusForeground":"#A4A4A4","list.errorForeground":"#C13838","list.warningForeground":"#c9a022","list.highlightForeground":"#c9a022","list.activeSelectionForeground":"#bbbbbb","list.activeSelectionBackground":"#464b5230","list.inactiveSelectionBackground":"#464b5230","list.hoverBackground":"#464b5215","list.hoverForeground":"#bbbbbb","gitDecoration.modifiedResourceForeground":"#3398DB","gitDecoration.deletedResourceForeground":"#C13838","gitDecoration.untrackedResourceForeground":"#37ae6f","gitDecoration.ignoredResourceForeground":"#464b52","gitDecoration.conflictingResourceForeground":"#76808c","menu.background":"#26282e","menu.foreground":"#A4A4A4","menu.separatorBackground":"#0b0c0e","menu.selectionForeground":"#A4A4A4","menubar.selectionBackground":"#26282e","menubar.selectionForeground":"#A4A4A4","menu.border":"#0b0c0e","merge.border":"#0b0c0e","merge.commonContentBackground":"#c9a02230","merge.commonHeaderBackground":"#c9a02280","merge.currentContentBackground":"#37ae6f30","merge.currentHeaderBackground":"#37ae6f80","merge.incomingContentBackground":"#3398DB30","merge.incomingHeaderBackground":"#3398DB80","editorOverviewRuler.border":"#0b0c0e","editorOverviewRuler.commonContentForeground":"#c9a022","editorOverviewRuler.currentContentForeground":"#C13838","editorOverviewRuler.incomingContentForeground":"#37ae6f","notificationCenterHeader.foreground":"#bbbbbb","notificationCenterHeader.background":"#26282e","notifications.foreground":"#A4A4A4","notifications.background":"#26282e","notifications.border":"#0b0c0e","notificationLink.foreground":"#c9a022","notificationsErrorIcon.foreground":"#C13838","notificationsWarningIcon.foreground":"#D26D32","notificationsInfoIcon.foreground":"#3398DB","panel.background":"#16181c","panel.border":"#0b0c0e","panelInput.border":"#464b52","panelSection.border":"#0b0c0e","panelTitle.activeBorder":"#76808c","panelTitle.activeForeground":"#76808c","panelTitle.inactiveForeground":"#464b52","panelSectionHeader.background":"#464b5220","panelSectionHeader.foreground":"#bbbbbb","panelSectionHeader.border":"#0b0c0e","peekView.border":"#76808c","peekViewEditor.background":"#26282e40","peekViewEditor.matchHighlightBackground":"#26282e40","peekViewResult.background":"#26282e40","peekViewResult.fileForeground":"#bbbbbb","peekViewResult.lineForeground":"#bbbbbb","peekViewResult.matchHighlightBackground":"#26282e","peekViewResult.selectionBackground":"#26282e","peekViewResult.selectionForeground":"#bbbbbb","peekViewTitle.background":"#0b0c0e","peekViewTitleDescription.foreground":"#bbbbbb","peekViewTitleLabel.foreground":"#bbbbbb","peekViewEditorGutter.background":"#26282e40","editorMarkerNavigation.background":"#141519","editorMarkerNavigationError.background":"#C1383890","editorMarkerNavigationWarning.background":"#c9a02290","editorMarkerNavigationInfo.background":"#3398DB90","editorError.border":"#00000000","editorError.foreground":"#C13838","pickerGroup.border":"#0b0c0e","pickerGroup.foreground":"#bbbbbb","progressBar.background":"#c9a022","scrollbar.shadow":"#00000000","scrollbarSlider.activeBackground":"#76808c40","scrollbarSlider.background":"#76808c20","scrollbarSlider.hoverBackground":"#76808c30","settings.modifiedItemIndicator":"#76808c","settings.headerForeground":"#76808c","sideBar.background":"#141519","sideBar.border":"#0b0c0e","sideBar.foreground":"#A4A4A4CC","sideBarSectionHeader.background":"#141519","sideBarSectionHeader.foreground":"#bbbbbb","sideBarSectionHeader.border":"#0b0c0e","sideBarTitle.foreground":"#464b52","tree.indentGuidesStroke":"#464b5270","statusBar.background":"#141519","statusBar.border":"#0b0c0e","statusBar.debuggingBackground":"#76808c44","statusBar.debuggingForeground":"#bbbbbb","statusBar.foreground":"#A4A4A4BB","statusBar.noFolderBackground":"#0b0c0e","statusBar.noFolderBorder":"#76808c","statusBar.noFolderForeground":"#bbbbbb","statusBarItem.activeBackground":"#26282e","statusBarItem.hoverBackground":"#464b5230","statusBarItem.prominentBackground":"#0b0c0e","statusBarItem.prominentHoverBackground":"#26282e","statusBarItem.errorBackground":"#C13838","editorSuggestWidget.background":"#181a1f","editorSuggestWidget.border":"#0b0c0e","editorSuggestWidget.foreground":"#A4A4A4","editorSuggestWidget.highlightForeground":"#c9a022","editorSuggestWidget.selectedBackground":"#76808c4d","editorGroupHeader.noTabsBackground":"#181a1f","editorGroupHeader.tabsBackground":"#141519","editorGroupHeader.tabsBorder":"#0b0c0e","editorGroupHeader.border":"#bb272700","tab.activeBackground":"#181a1f","tab.activeForeground":"#76808c","tab.activeBorderTop":"#76808c","tab.activeBorder":"#181a1f","tab.border":"#0b0c0e","tab.hoverBorder":"#00000000","tab.hoverBackground":"#181a1fcc","tab.unfocusedHoverBackground":"#76808c10","tab.unfocusedHoverBorder":"#00000000","tab.inactiveBackground":"#141519","tab.inactiveForeground":"#464b52","tab.unfocusedActiveForeground":"#bbbbbb","tab.unfocusedInactiveForeground":"#bbbbbb","tab.lastPinnedBorder":"#0b0c0e","terminal.ansiBlack":"#181a1f","terminal.ansiRed":"#C13838","terminal.ansiGreen":"#37ae6f","terminal.ansiYellow":"#c9a022","terminal.ansiBlue":"#3398DB","terminal.ansiMagenta":"#CC71BC","terminal.ansiCyan":"#24B5A8","terminal.ansiWhite":"#bbbbbb","terminal.ansiBrightBlack":"#3398DB","terminal.ansiBrightRed":"#C13838","terminal.ansiBrightGreen":"#37ae6f","terminal.ansiBrightYellow":"#c9a022","terminal.ansiBrightBlue":"#3398DB","terminal.ansiBrightMagenta":"#CC71BC","terminal.ansiBrightCyan":"#24B5A8","terminal.ansiBrightWhite":"#bbbbbb","terminal.background":"#16181c","terminal.foreground":"#bbbbbb","terminalCursor.background":"#c9a022","terminalCursor.foreground":"#c9a022","terminal.selectionForeground":"#bbbbbb","textBlockQuote.background":"#3398DB34","textBlockQuote.border":"#3398DBb9","textCodeBlock.background":"#3398DB34","textLink.activeForeground":"#3398DB","textLink.foreground":"#3398DB","textPreformat.foreground":"#c9a022","textSeparator.foreground":"#76808c","walkThrough.embeddedEditorBackground":"#181a1f","titleBar.activeBackground":"#141519","titleBar.activeForeground":"#464b52","titleBar.inactiveBackground":"#0b0c0e","titleBar.inactiveForeground":"#464b52","titleBar.border":"#0b0c0e"},"tokenColors":[{"scope":["support.module.elm","entity.other.inherited-class.python","variable.other.object","support.other.namespace.php","entity.other.attribute-name.namespace.xml","record.accessor","entity.name.record.field.accessor","storage.modifier.import.java","storage.modifier.import.groovy","meta.import.swift entity.name.type.swift","entity.name.variable.parameter.cs","meta.member.access.python","variable.other.property.ts","variable.other.property.js","constant.language.symbol.elixir"],"settings":{"foreground":"#D26D32"}},{"scope":["entity.name.type"],"settings":{"foreground":"#7E9E2D"}},{"scope":["comment","punctuation.definition.comment","string.quoted.docstring.multi","comment.block.documentation source"],"settings":{"foreground":"#464b52","fontStyle":"italic"}},{"scope":["constant"],"settings":{"foreground":"#C13838"}},{"scope":["source","support","constant.character.entity.named","meta.jsx.children","source.lua","text.html.derivative"],"settings":{"foreground":"#A4A4A4"}},{"scope":["entity.name.function.decorator","meta.decorator entity.name.function","meta.decorator punctuation.decorator","punctuation.definition.decorator","meta.decorator variable.other.readwrite.ts"],"settings":{"foreground":"#CC71BC"}},{"scope":["keyword.control.export","support.type.object.module"],"settings":{"foreground":"#c9a022"}},{"scope":["support.function","entity.name.function","meta.function-call","meta.function","meta.method.declaration","meta.function-call support","meta.decorator meta.definition.method entity.name.function","meta.decorator meta.method.declaration entity.name.function","variable.language.super.ts","source.directive","meta.function-call.generic","meta.method-call.static.php","meta.method-call.php","meta.class storage.type","meta.method.groovy","meta.bracket.square.access","entity.name.function-call.elixir","punctuation.output.liquid support.variable.liquid","meta.function.echo.edge source.js keyword.operator.error-control.js"],"settings":{"foreground":"#3398DB"}},{"scope":["keyword.control.import","meta.module.name.elm support","meta.import.elm support","keyword.control.at-rule","punctuation.definition.keyword","variable.control.import.include","keyword.other.import.java"],"settings":{"foreground":"#c9a022"}},{"scope":["keyword.control","keyword.control.conditional","storage.modifier","keyword.operator.new","keyword.operator.expression","keyword.begin.blade","keyword.end.blade","keyword.blade","keyword.type-alias","keyword.type","support.class.console","keyword.other.await","storage.type.class.jsdoc","punctuation.definition.block.tag.jsdoc","keyword.other.new","keyword.other.phpdoc","keyword.other.use.php","keyword.operator.logical.python","keyword.other.import.static.groovy","keyword.other.import.groovy","punctuation.definition.attribute.swift","source.svelte meta.scope.tag.main.svelte meta.tag.start.svelte variable.function.svelte","meta.directive.on.svelte entity.name.type.svelte","keyword.other.special-method.elixir","keyword.edge","entity.name.function.edge","support.constant.edge"],"settings":{"foreground":"#c9a022"}},{"scope":["meta.object-literal.key","variable.object.property"],"settings":{"foreground":"#bbbbbb"}},{"scope":["keyword.other.definition.ini","support.type.property-name","entity.name.tag.yaml"],"settings":{"foreground":"#c9a022"}},{"scope":["keyword.operator.comparison","storage.type.function.arrow","keyword.operator.lua","keyword.operator.assignment","keyword.operator.relational","keyword.operator.increment","keyword.operator.decrement","keyword.operator.logical","keyword.operator.arithmetic","keyword.operator.math"],"settings":{"foreground":"#c9a022"}},{"scope":["punctuation","attribute_value","meta.brace","punctuation.definition.parameters","punctuation.definition.template-expression","keyword.operator","keyword.other","punctuation.terminator","punctuation.separator","punctuation.definition.generic.begin","punctuation.definition.generic.end","meta.function.type-declaration","keyword.other.colon.elm","meta.record.field.elm keyword.other.elm","keyword.other.period.elm","meta.tag.xml","meta.tag.preprocessor.xml","punctuation.definition.block","punctuation.accessor","constant.name.attribute.tag.pug","string.interpolated.pug","keyword.other.whitespace.liquid","meta.tag.template.block.twig","meta.tag.template.value.twig","begin.bracket","end.bracket","text.html.twig meta.tag.inline.any","text.html.twig meta.tag.block.any","support.function.construct.begin.blade","support.function.construct.end.blade source.php","support.function.construct.end.blade","meta.function.echo.blade source.php","punctuation.definition.list.begin.python","punctuation.definition.list.end.python","text.html.vue-html meta.tag.block.any","entity.name.variable.tuple-element.cs","keyword.operator.assignment.tsx","meta.definition.method.signature.java","meta.class.body.groovy","meta.definition.method.groovy meta.method.body.java meta.declaration.assertion.groovy","punctuation.definition.list.begin.erlang","meta.expression.parenthesized","meta.definition.function.swift meta.parameter-clause.swift","source.swift meta.function-call.swift","punctuation.section.embedded.end.swift source.swift","source.lua","meta.function.lua","punctuation.definition.keyword.svelte","source.svelte meta.scope.tag.SpeakerPicture.svelte meta.tag.start.svelte entity.other.attribute-name.svelte","expression.embbeded.vue punctuation.definition.tag.begin.html.vue","expression.embbeded.vue punctuation.definition.tag.end.html.vue"],"settings":{"foreground":"#bbbbbb60"}},{"scope":["variable.language.this","variable.language.special.self","variable.parameter.function.language.special.self","variable.language.this.php punctuation.definition.variable.php","meta.class.body.php storage.type.php","variable.parameter.function.swift entity.name.function.swift","variable.other.jsdoc"],"settings":{"foreground":"#D26D32"}},{"scope":["storage","meta.var.expr storage.type","storage.type.function","keyword.function","storage.type.class","storage.type.property","keyword.other","keyword.local.lua","entity.name.class","meta.function.lua keyword.control.lua","storage.type.enum","storage.type.interface","storage.type.type","entity.name.type.class.java","support.class.php","entity.name.type.class.php","entity.other.inherited-class.php","entity.name.type.class.groovy","storage.type.rust  ","entity.name.type.class.swift","source.svelte meta.script.svelte source.ts entity.name.label.ts","meta.directive.on.svelte keyword.control.svelte"],"settings":{"foreground":"#24B5A8"}},{"scope":["string","string.template","string.quoted.single","punctuation.definition.string","punctuation.definition.string.template","punctuation.definition.string.begin","punctuation.definition.string.end.html source.js-ignored-vscode","punctuation.definition.string.end","string.other.link","constant.character.escape.regexp","variable.parameter.url","constant.other.symbol.quoted.single.erlang","constant.other.symbol.quoted.single.erlang punctuation.definition.symbol.begin.erlang","constant.other.symbol.quoted.single.erlang punctuation.definition.symbol.end.erlang","meta.import.ts punctuation.definition.variable.svelte","punctuation.definition.string.end.html source.css-ignored-vscode","text.html.edge punctuation.definition.variable.js"],"settings":{"foreground":"#37ae6f"}},{"scope":["string.quoted.docstring.multi.python","string.quoted.double.block.python punctuation.definition.string.end.python","string.quoted.double.block.python punctuation.definition.string.begin.python","string.quoted.double.block.python"],"settings":{"foreground":"#37ae6f60"}},{"scope":["entity.name.type","support.type","support.class","storage.type","entity.other.inherited-class","keyword.type","storage.type.java","storage.type.primitive.java","storage.type.generic.java","keyword.other.type","punctuation.section.embedded.begin.php","punctuation.section.embedded.end.php source.php","punctuation.section.embedded.end.php","storage.type.object.array.java","storage.type.primitive.groovy","storage.type.groovy","meta.definition.type.body.swift meta.function-call.swift","meta.definition.type.class.swift meta.inheritance-clause.swift","variable.other.constant.elixir"],"settings":{"foreground":"#935cd1"}},{"scope":["variable","variable.language","entity.name.type.class.js","entity.name.variable","support.variable.magic","meta.method.body","entity.name.variable","punctuation.definition.variable","meta.class variable.object.property","variable.other.constant entity.name.function","entity.name.variable.tuple-element.cs punctuation.separator.colon.cs","meta.definition.variable.name.groovy","meta.body.struct.cpp","parameter.variable.function.elixir","meta.directive.edge source.js","meta.function.echo.edge source.js","text.html.edge meta.function.echo.edge meta.function-call.js","source.css variable.parameter.keyframe-list.css","source.css meta.property-value.css","source.css.scss meta.at-rule.keyframes.scss entity.name.function.scss","source.css.scss meta.property-value.scss"],"settings":{"foreground":"#de456b"}},{"scope":["source.elm constant.type-constructor"],"settings":{"foreground":"#de456b"}},{"scope":["source.elm storage.type"],"settings":{"foreground":"#935cd1","fontStyle":"normal"}},{"scope":["entity.name.tag.other.html","meta.tag.other.html punctuation.definition.tag.end.html","meta.tag.other.html punctuation.definition.tag.begin.html","entity.name.tag support.class.component","support.class.component.html"],"settings":{"foreground":"#3398DB"}},{"scope":["source.diff meta.diff.header.to-file","source.diff markup.inserted.diff","source.diff punctuation.definition.to-file.diff","source.diff punctuation.definition.inserted.diff"],"settings":{"foreground":"#37ae6f"}},{"scope":["source.diff punctuation.definition.from-file.diff","source.diff meta.diff.header.from-file","source.diff markup.deleted.diff","source.diff punctuation.definition.deleted.diff"],"settings":{"foreground":"#C13838"}},{"scope":["source.diff meta.diff.header.command"],"settings":{"foreground":"#3398DB"}},{"scope":["source.diff punctuation.definition.range.diff","source.diff meta.diff.range.unified"],"settings":{"foreground":"#D26D32"}},{"scope":["support.variable.liquid","support.class.liquid"],"settings":{"foreground":"#de456b"}},{"scope":["text.html.basic entity.name","source.js-ignored-vscode","entity.name.tag","meta.embedded.block.blade constant.other.php","meta.embedded.block.blade keyword.operator.comparison.php","meta.embedded.block.blade keyword.operator.arithmetic.php","meta.tag.start.svelte keyword.control.svelte","meta.tag.end.svelte keyword.control.svelte"],"settings":{"foreground":"#3398DB"}},{"scope":["meta.tag.sgml.doctype.html","punctuation.definition.tag","meta.tag.block.any","meta.tag.block.any.html","meta.tag.inline.any","source.css-ignored-vscode","meta.tag.metadata.style.end.html","text.html.vue invalid.illegal.character-not-allowed-here.html","meta.tag.inline.i.start.html","meta.tag.structure.div.start.html","punctuation.definition.tag.end.html.vue","invalid.illegal.character-not-allowed-here.html"],"settings":{"foreground":"#3398DBaa"}},{"scope":["entity.other.attribute-name","entity.name.tag.liquid","invalid.deprecated.entity.other.attribute-name","meta.embedded.block.blade storage.type.php"],"settings":{"foreground":"#c9a022"}},{"scope":["markup.inline.raw.string.markdown","punctuation.definition.raw.markdown","markup.fenced_code.block.markdown","markup.fenced_code.block.markdown punctuation","markup.raw.block.markdown"],"settings":{"foreground":"#935cd1"}},{"scope":["fenced_code.block.language"],"settings":{"foreground":"#935cd1"}},{"scope":["punctuation.definition.list.begin"],"settings":{"foreground":"#3398DB"}},{"scope":["punctuation.definition.list.begin"],"settings":{"foreground":"#3398DB"}},{"scope":["entity.name.section","markup.heading.setext"],"settings":{"foreground":"#c9a022"}},{"scope":["punctuation.definition.heading"],"settings":{"foreground":"#c9a022"}},{"scope":["markup.underline.link","markup.underline.link.image"],"settings":{"foreground":"#3398DB"}},{"scope":["markup.bold","punctuation.definition.bold"],"settings":{"foreground":"#de456b","fontStyle":"bold"}},{"scope":["markup.strikethrough","punctuation.definition.strikethrough"],"settings":{"foreground":"#C13838"}},{"scope":["markup.italic","punctuation.definition.italic"],"settings":{"foreground":"#D26D32","fontStyle":"italic"}},{"scope":["markup.quote","markup.quote.markdown punctuation.definition.quote.begin"],"settings":{"foreground":"#CC71BC"}},{"scope":["punctuation.definition.quote.begin"],"settings":{"foreground":"#3398DB"}},{"scope":["meta.embedded.block.frontmatter punctuation.definition.tag.begin","meta.embedded.block.frontmatter punctuation.definition.tag.end","meta.embedded.block.frontmatter string.unquoted.plain.out"],"settings":{"foreground":"#464b52","fontStyle":"italic"}},{"scope":["entity.other.attribute-name.pseudo-class"],"settings":{"foreground":"#CC71BC"}},{"scope":["entity.other.attribute-name.pseudo-element"],"settings":{"foreground":"#CC71BC"}},{"scope":["entity.other.attribute-name.class","entity.other.attribute-name.class punctuation.definition.entity"],"settings":{"foreground":"#24B5A8"}},{"scope":["entity.other.attribute-name.parent-selector-suffix punctuation.definition.entity"],"settings":{"foreground":"#24B5A8"}},{"scope":["support.type.property-name.css","support.type.vendored.property-name","meta.property-list entity.name.tag.css","meta.property-list.scss meta.property-list.scss entity.name.tag.css","meta.property-list meta.property-name","source.css.scss meta.property-list.scss entity.name.tag.css"],"settings":{"foreground":"#bbbbbb"}},{"scope":["source.css.scss entity.other.attribute-name.id ","source.css entity.other.attribute-name.id ","entity.other.attribute-name.id punctuation.definition.entity"],"settings":{"foreground":"#935cd1"}},{"scope":["entity.name.tag.reference","meta.property-list"],"settings":{"foreground":"#D26D32"}},{"scope":["keyword.other.unit"],"settings":{"foreground":"#D26D32"}},{"scope":["support.constant.property-value","support.constant.font-name","meta.property-value.css","meta.attribute.style.html"],"settings":{"foreground":"#D26D32"}},{"scope":["constant.numeric"],"settings":{"foreground":"#D26D32"}},{"scope":["entity.name.tag.css","meta.property-list.scss entity.name.tag.css"],"settings":{"foreground":"#3398DB"}}]}